learner/__init__.py
learner/base.py
learner/callbacks.py
learner/data.py
learner/device.py
learner/metrics.py
learner/models/__init__.py
learner/models/ae.py
learner/models/vision.py
learner/trainer.py
learner/wrappers/__init__.py
learner/wrappers/sklearn.py
learner-0.1.3.dist-info/WHEEL
learner-0.1.3.dist-info/METADATA
learner-0.1.3.dist-info/RECORD
